{
  "kind": "collectionType",
  "collectionName": "contents",
  "info": {
    "singularName": "content",
    "pluralName": "contents",
    "displayName": "content",
    "description": ""
  },
  "options": {
    "draftAndPublish": true
  },
  "pluginOptions": {},
  "attributes": {
    "title": {
      "type": "string"
    },
    "duration": {
      "type": "string"
    },
    "file": {
      "type": "media",
      "multiple": false,
      "required": false,
      "allowedTypes": [
        "images",
        "files",
        "videos",
        "audios"
      ]
    },
    "course": {
      "type": "relation",
      "relation": "manyToOne",
      "target": "api::course.course",
      "inversedBy": "contents"
    },
    "is_free": {
      "type": "boolean",
      "required": true
    }
  }
}
